lingjing/__init__.py
lingjing-1.0.0.dist-info/LICENSE
lingjing-1.0.0.dist-info/METADATA
lingjing-1.0.0.dist-info/WHEEL
lingjing-1.0.0.dist-info/top_level.txt
lingjing-1.0.0.dist-info/RECORD
